marqo_haystack/__about__.py
marqo_haystack/__init__.py
marqo_haystack/document_store.py
marqo_haystack/errors.py
marqo_haystack/retriever.py
marqo_haystack-0.1.0.dist-info/METADATA
marqo_haystack-0.1.0.dist-info/WHEEL
marqo_haystack-0.1.0.dist-info/licenses/LICENSE
marqo_haystack-0.1.0.dist-info/RECORD
