Metadata-Version: 2.1
Name: marqo-haystack
Version: 0.1.0
Project-URL: Documentation, https://github.com/marqo-ai/marqo-haystack#readme
Project-URL: Issues, https://github.com/marqo-ai/marqo-haystack/issues
Project-URL: Source, https://github.com/marqo-ai/marqo-haystack
Author-email: Owen Elliott <owen@marqo.ai>
License-Expression: Apache-2.0
License-File: LICENSE
Classifier: Development Status :: 4 - Beta
Classifier: Programming Language :: Python
Classifier: Programming Language :: Python :: 3.9
Classifier: Programming Language :: Python :: 3.10
Classifier: Programming Language :: Python :: 3.11
Classifier: Programming Language :: Python :: Implementation :: CPython
Classifier: Programming Language :: Python :: Implementation :: PyPy
Requires-Python: >=3.9
Requires-Dist: haystack-ai
Requires-Dist: marqo
